dqt/__init__.py
dqt/cli.py
dqt-0.1.6.dist-info/METADATA
dqt-0.1.6.dist-info/WHEEL
dqt-0.1.6.dist-info/entry_points.txt
dqt-0.1.6.dist-info/RECORD
