Metadata-Version: 2.4
Name: dqt
Version: 0.1.6
Summary: A tool to check and monitor the quality of your data.
Requires-Python: >=3.10
Requires-Dist: ascii>=3.6
Requires-Dist: click>=8.1.8
Requires-Dist: loguru>=0.7.3
